gratient/__init__.py
gratient-0.5.dist-info/METADATA
gratient-0.5.dist-info/WHEEL
gratient-0.5.dist-info/top_level.txt
gratient-0.5.dist-info/RECORD
